whois_parser/__init__.py
whois_parser/dataclasses.py
whois_parser/parser.py
whois_parser/parsers/__init__.py
whois_parser/parsers/abstract.py
whois_parser/parsers/base.py
whois_parser/parsers/be.py
whois_parser/parsers/constants.py
whois_parser/parsers/jp.py
whois_parser/parsers/uk.py
whois_parser/parsers/utils.py
whois_parser/settings.py
whois_parser-0.3.1.dist-info/LICENSE
whois_parser-0.3.1.dist-info/METADATA
whois_parser-0.3.1.dist-info/WHEEL
whois_parser-0.3.1.dist-info/RECORD
