Metadata-Version: 2.1
Name: whois-parser
Version: 0.3.1
Summary: Yet another whois parser for Python
Home-page: https://github.com/ninoseki/whois-parser
Author: Manabu Niseki
Author-email: manabu.niseki@gmail.com
Requires-Python: >=3.9,<4.0
Classifier: Programming Language :: Python :: 3
Classifier: Programming Language :: Python :: 3.9
Classifier: Programming Language :: Python :: 3.10
Classifier: Programming Language :: Python :: 3.11
Requires-Dist: dateparser (>=1.1,<2.0)
Requires-Dist: pyparsing (>=3.1,<4.0)
Project-URL: Repository, https://github.com/ninoseki/whois-parser
